desafio_banco/__init__.py
desafio_banco/desafio.py
desafio_banco-0.0.1.dist-info/METADATA
desafio_banco-0.0.1.dist-info/WHEEL
desafio_banco-0.0.1.dist-info/top_level.txt
desafio_banco-0.0.1.dist-info/RECORD
