Metadata-Version: 2.4
Name: desafio_banco
Version: 0.0.1
Summary: Desafio Banco - Projeto de Python DIO
Home-page: https://github.com/BrunoRodri/simple-package-template
Author: bruno_rodrigues
Author-email: fidbruno@hotmail.com
Requires-Python: >=3.8
Dynamic: author
Dynamic: author-email
Dynamic: description
Dynamic: description-content-type
Dynamic: home-page
Dynamic: requires-python
Dynamic: summary
